{
  "theme_name": "Sound Cloud Theme",
  "version": "1.0.0",
  "import_data": {
    "pages": [
      {
        "title": "Downloader",
        "slug": "downloader",
        "content": "This is the SoundCloud downloader page. Use the form below to download your favorite tracks.",
        "template": "page-downloader.php",
        "status": "publish",
        "meta": {
          "_wp_page_template": "page-downloader.php"
        }
      },
      {
        "title": "About Us",
        "slug": "about",
        "content": "Learn more about our mission and team.",
        "template": "page-about.php",
        "status": "publish",
        "meta": {
          "_wp_page_template": "page-about.php"
        }
      },
      {
        "title": "Privacy Policy",
        "slug": "privacy-policy",
        "content": "Our privacy policy and data protection information.",
        "template": "page-privacy.php",
        "status": "publish",
        "meta": {
          "_wp_page_template": "page-privacy.php"
        }
      },
      {
        "title": "Contact Us",
        "slug": "contact",
        "content": "Get in touch with our support team.",
        "template": "page-contact.php",
        "status": "publish",
        "meta": {
          "_wp_page_template": "page-contact.php"
        }
      },
      {
        "title": "FAQ",
        "slug": "faq",
        "content": "Frequently asked questions about our service.",
        "template": "page-faq.php",
        "status": "publish",
        "meta": {
          "_wp_page_template": "page-faq.php"
        }
      },
      {
        "title": "Blog",
        "slug": "blog",
        "content": "Our latest blog posts and updates.",
        "status": "publish"
      }
    ],
    "posts": [
      {
        "title": "How to Download Music from SoundCloud: A Complete Guide",
        "slug": "how-to-download-music-from-soundcloud-complete-guide",
        "content": "SoundCloud is one of the most popular platforms for discovering and sharing music. Whether you're an artist looking to promote your tracks or a music lover wanting to download your favorite songs, this guide will walk you through everything you need to know about downloading music from SoundCloud.\n\n## Why Download from SoundCloud?\n\nSoundCloud hosts millions of tracks from both established artists and emerging talents. Downloading music from SoundCloud allows you to:\n\n- Listen to music offline\n- Create personal playlists\n- Support independent artists\n- Access exclusive content\n- Build your music library\n\n## Legal Considerations\n\nBefore downloading any music, it's important to understand the legal aspects:\n\n- Only download content you have permission to use\n- Respect copyright laws and artist rights\n- Support artists through official channels when possible\n- Use downloaded content for personal use only\n\n## Step-by-Step Download Process\n\n1. **Find the Track**: Browse SoundCloud or use the search function to find your desired track\n2. **Copy the URL**: Right-click on the track and copy the link\n3. **Use Our Downloader**: Paste the URL into our downloader tool\n4. **Select Quality**: Choose your preferred audio quality (128kbps, 256kbps, 320kbps, or FLAC)\n5. **Download**: Click the download button and wait for processing\n\n## Audio Quality Options\n\nOur downloader supports multiple audio formats:\n\n- **MP3 128kbps**: Standard quality, smaller file size\n- **MP3 256kbps**: Good quality, balanced file size\n- **MP3 320kbps**: High quality, larger file size\n- **FLAC**: Lossless quality, largest file size\n\n## Tips for Best Results\n\n- Ensure you have a stable internet connection\n- Check that the track is publicly available\n- Verify the track hasn't been deleted or made private\n- Be patient during processing, especially for longer tracks\n\n## Troubleshooting Common Issues\n\n**Download Failed**: Try refreshing the page and attempting again\n**Slow Processing**: This is normal for longer tracks or high-quality downloads\n**Invalid URL**: Make sure you're using a valid SoundCloud track URL\n**Network Error**: Check your internet connection and try again\n\n## Supporting Artists\n\nRemember that downloading music is just one way to enjoy content. Consider:\n\n- Following artists on SoundCloud\n- Sharing tracks you enjoy\n- Purchasing music through official channels\n- Attending live performances\n- Supporting artists on other platforms\n\n## Conclusion\n\nDownloading music from SoundCloud can be a great way to build your personal music library and discover new artists. By following this guide and respecting copyright laws, you can enjoy your favorite tracks while supporting the music community.\n\nHappy listening!",
        "excerpt": "Learn how to download music from SoundCloud with our complete guide. Step-by-step instructions, legal considerations, and tips for the best results.",
        "status": "publish",
        "featured_image": "https://via.placeholder.com/800x400/667eea/ffffff?text=SoundCloud+Download+Guide"
      },
      {
        "title": "Best SoundCloud Downloader Tools in 2024",
        "slug": "best-soundcloud-downloader-tools-2024",
        "content": "With millions of tracks available on SoundCloud, having the right downloader tool is essential for music enthusiasts. In this comprehensive review, we'll explore the best SoundCloud downloader tools available in 2024.\n\n## What Makes a Great SoundCloud Downloader?\n\nBefore diving into our recommendations, let's understand what features make a downloader tool stand out:\n\n### Essential Features\n- **Multiple Format Support**: MP3, FLAC, WAV, M4A\n- **Quality Options**: Various bitrates from 128kbps to lossless\n- **Fast Processing**: Quick download times\n- **User-Friendly Interface**: Easy to use for all skill levels\n- **Privacy Protection**: No data collection or tracking\n- **Free to Use**: No hidden costs or subscriptions\n\n### Advanced Features\n- **Batch Downloads**: Download multiple tracks at once\n- **Playlist Support**: Download entire playlists\n- **Metadata Preservation**: Keep original track information\n- **Mobile Compatibility**: Works on all devices\n- **Cloud Storage Integration**: Direct upload to cloud services\n\n## Top SoundCloud Downloader Tools\n\n### 1. Our SoundCloud Downloader\n**Rating: 5/5**\n\nOur proprietary downloader offers the best combination of features and performance:\n\n**Pros:**\n- Lightning-fast processing\n- Multiple quality options\n- Completely free\n- No registration required\n- Mobile-friendly interface\n- Privacy-focused\n\n**Cons:**\n- Individual track downloads only\n- No playlist support yet\n\n### 2. SoundCloud Downloader Pro\n**Rating: 4.5/5**\n\nA popular choice among music enthusiasts:\n\n**Pros:**\n- Batch download support\n- Playlist integration\n- Advanced quality settings\n- User-friendly interface\n\n**Cons:**\n- Limited free version\n- Requires registration for full features\n- Some privacy concerns\n\n### 3. Music Downloader Plus\n**Rating: 4/5**\n\nA solid option for basic downloading needs:\n\n**Pros:**\n- Simple interface\n- Good quality output\n- Reliable performance\n- Free to use\n\n**Cons:**\n- Limited format options\n- Slower processing\n- Basic features only\n\n## Quality Comparison\n\n| Tool | MP3 Quality | FLAC Support | Processing Speed | User Rating |\n|------|-------------|--------------|------------------|-------------|\n| Our Downloader | 320kbps | Yes | Fast | 5/5 |\n| Downloader Pro | 256kbps | Yes | Medium | 4.5/5 |\n| Music Plus | 192kbps | No | Slow | 4/5 |\n\n## How to Choose the Right Tool\n\n### For Casual Users\n- Simple interface\n- Basic quality options\n- Free to use\n- No registration required\n\n### For Power Users\n- Advanced features\n- Batch processing\n- Multiple format support\n- Custom quality settings\n\n### For Mobile Users\n- Responsive design\n- Touch-friendly interface\n- Fast loading\n- Offline capability\n\n## Legal and Ethical Considerations\n\n### Always Remember:\n- Only download content you have permission to use\n- Respect artist copyrights\n- Support artists through official channels\n- Use downloaded content for personal use only\n- Don't redistribute copyrighted material\n\n### Best Practices:\n- Check track licensing before downloading\n- Support independent artists\n- Share tracks through official platforms\n- Attend live performances when possible\n\n## Troubleshooting Common Issues\n\n### Download Failures\n- Check internet connection\n- Verify track is publicly available\n- Try different quality settings\n- Clear browser cache\n\n### Quality Issues\n- Select higher bitrate\n- Use FLAC for lossless quality\n- Check original track quality\n- Verify download completion\n\n### Performance Problems\n- Close other applications\n- Use wired internet connection\n- Try during off-peak hours\n- Update browser/application\n\n## Future of SoundCloud Downloading\n\n### Emerging Trends:\n- AI-powered quality enhancement\n- Real-time processing\n- Cloud integration\n- Mobile-first design\n- Enhanced privacy protection\n\n### Upcoming Features:\n- Playlist batch downloads\n- Social sharing integration\n- Advanced metadata editing\n- Cross-platform synchronization\n\n## Conclusion\n\nChoosing the right SoundCloud downloader depends on your specific needs and usage patterns. For most users, our downloader offers the best balance of features, performance, and ease of use.\n\nRemember to always respect copyright laws and support artists through official channels. Happy downloading!",
        "excerpt": "Discover the best SoundCloud downloader tools in 2024. Compare features, quality, and performance to find the perfect tool for your needs.",
        "status": "publish",
        "featured_image": "https://via.placeholder.com/800x400/764ba2/ffffff?text=Downloader+Tools+2024"
      },
      {
        "title": "Understanding Audio Quality: MP3 vs FLAC vs WAV",
        "slug": "understanding-audio-quality-mp3-flac-wav",
        "content": "When downloading music from SoundCloud, choosing the right audio format and quality is crucial for the best listening experience. This guide will help you understand the differences between MP3, FLAC, and WAV formats.\n\n## Audio Quality Basics\n\n### What is Bitrate?\nBitrate refers to the amount of data processed per second in an audio file. Higher bitrates generally mean better audio quality but larger file sizes.\n\n**Common Bitrates:**\n- 128 kbps: Standard quality, good for casual listening\n- 256 kbps: High quality, balanced size and quality\n- 320 kbps: Very high quality, near-CD quality\n- 1411 kbps: CD quality (uncompressed)\n\n## MP3 Format\n\n### Overview\nMP3 (MPEG Audio Layer III) is the most popular audio format due to its compression efficiency and wide compatibility.\n\n### Advantages:\n- **Small File Size**: 90% smaller than uncompressed audio\n- **Universal Compatibility**: Works on all devices and players\n- **Fast Processing**: Quick to download and convert\n- **Wide Support**: Supported by all major platforms\n\n### Disadvantages:\n- **Lossy Compression**: Some audio data is permanently lost\n- **Quality Loss**: Not suitable for professional use\n- **Limited Dynamic Range**: Compressed audio has less detail\n\n### Best For:\n- Casual listening\n- Mobile devices with limited storage\n- Streaming services\n- General music consumption\n\n## FLAC Format\n\n### Overview\nFLAC (Free Lossless Audio Codec) provides lossless compression, meaning no audio data is lost during compression.\n\n### Advantages:\n- **Lossless Quality**: Identical to original source\n- **Smaller than WAV**: 50-70% compression without quality loss\n- **Metadata Support**: Preserves all track information\n- **Open Source**: Free and widely supported\n\n### Disadvantages:\n- **Larger File Size**: 2-3x larger than MP3\n- **Limited Compatibility**: Not supported by all devices\n- **Processing Power**: Requires more CPU for playback\n- **Storage Requirements**: Needs more disk space\n\n### Best For:\n- Audiophiles and music enthusiasts\n- Professional audio work\n- Archival purposes\n- High-quality sound systems\n\n## WAV Format\n\n### Overview\nWAV (Waveform Audio File Format) is an uncompressed audio format that preserves the original audio data exactly.\n\n### Advantages:\n- **Perfect Quality**: No compression artifacts\n- **Universal Compatibility**: Works on all systems\n- **Professional Standard**: Used in professional audio\n- **No Processing**: Direct audio data\n\n### Disadvantages:\n- **Large File Size**: 10x larger than MP3\n- **Storage Intensive**: Requires significant disk space\n- **Slow Transfer**: Takes longer to download\n- **Limited Metadata**: Basic information only\n\n### Best For:\n- Professional audio production\n- Archival and backup purposes\n- Critical listening environments\n- When maximum quality is required\n\n## Quality Comparison\n\n| Format | File Size | Quality | Compatibility | Use Case |\n|--------|-----------|---------|---------------|----------|\n| MP3 128kbps | Small | Good | Excellent | Casual listening |\n| MP3 256kbps | Medium | Very Good | Excellent | General use |\n| MP3 320kbps | Large | Excellent | Excellent | High-quality listening |\n| FLAC | Large | Perfect | Good | Audiophile |\n| WAV | Very Large | Perfect | Excellent | Professional |\n\n## Choosing the Right Format\n\n### For Mobile Devices\n- **MP3 256kbps**: Best balance of quality and size\n- **MP3 320kbps**: If storage allows\n- **Avoid FLAC/WAV**: Too large for mobile storage\n\n### For Desktop/Laptop\n- **MP3 320kbps**: Excellent quality with reasonable size\n- **FLAC**: If you have storage space and quality equipment\n- **WAV**: Only for professional use or archival\n\n### For Audiophile Systems\n- **FLAC**: Perfect for high-end audio systems\n- **WAV**: If you need maximum compatibility\n- **MP3 320kbps**: Minimum acceptable quality\n\n## Storage Requirements\n\n### File Size Estimates (3-minute song):\n- MP3 128kbps: ~3 MB\n- MP3 256kbps: ~6 MB\n- MP3 320kbps: ~7.5 MB\n- FLAC: ~15-25 MB\n- WAV: ~30-50 MB\n\n### Storage Planning:\n- **1GB**: ~300 MP3 songs (128kbps)\n- **1GB**: ~150 MP3 songs (256kbps)\n- **1GB**: ~40 FLAC songs\n- **1GB**: ~20 WAV songs\n\n## Technical Considerations\n\n### Processing Power\n- **MP3**: Low CPU usage, fast processing\n- **FLAC**: Medium CPU usage, moderate processing\n- **WAV**: Low CPU usage, but large file transfers\n\n### Network Requirements\n- **MP3**: Fast downloads, suitable for mobile data\n- **FLAC**: Slower downloads, requires good connection\n- **WAV**: Very slow downloads, needs stable connection\n\n## Our Recommendations\n\n### For Most Users: MP3 320kbps\n- Excellent quality\n- Reasonable file size\n- Universal compatibility\n- Fast downloads\n\n### For Audiophiles: FLAC\n- Lossless quality\n- Perfect for high-end systems\n- Preserves all audio data\n- Future-proof format\n\n### For Professionals: WAV\n- Maximum compatibility\n- No compression artifacts\n- Professional standard\n- Perfect quality preservation\n\n## Conclusion\n\nThe choice between MP3, FLAC, and WAV depends on your specific needs:\n\n- **Storage space**: MP3 for limited space, FLAC/WAV for abundant space\n- **Audio equipment**: Basic systems work fine with MP3, high-end systems benefit from FLAC\n- **Usage purpose**: Casual listening (MP3), serious listening (FLAC), professional (WAV)\n- **Compatibility needs**: MP3 for universal support, FLAC for quality, WAV for maximum compatibility\n\nRemember, the best format is the one that meets your specific needs while providing the quality you desire. Our downloader supports all these formats, so you can choose what works best for you!",
        "excerpt": "Learn about audio quality differences between MP3, FLAC, and WAV formats. Choose the right format for your listening needs and equipment.",
        "status": "publish",
        "featured_image": "https://via.placeholder.com/800x400/ff6b6b/ffffff?text=Audio+Quality+Guide"
      },
      {
        "title": "SoundCloud vs Other Music Platforms: A Complete Comparison",
        "slug": "soundcloud-vs-other-music-platforms-comparison",
        "content": "The music streaming landscape is more diverse than ever, with each platform offering unique features and benefits. In this comprehensive comparison, we'll explore how SoundCloud stacks up against other major music platforms.\n\n## Platform Overview\n\n### SoundCloud\n- **Founded**: 2007\n- **Users**: 175+ million\n- **Content**: User-generated and professional\n- **Focus**: Independent artists and discovery\n\n### Spotify\n- **Founded**: 2006\n- **Users**: 400+ million\n- **Content**: Licensed music\n- **Focus**: Mainstream music streaming\n\n### Apple Music\n- **Founded**: 2015\n- **Users**: 80+ million\n- **Content**: Licensed music\n- **Focus**: Premium music experience\n\n### YouTube Music\n- **Founded**: 2015\n- **Users**: 50+ million\n- **Content**: Music videos and audio\n- **Focus**: Video and audio integration\n\n## Content and Discovery\n\n### SoundCloud Advantages\n- **Independent Artists**: Largest platform for emerging talent\n- **Unique Content**: Exclusive tracks and remixes\n- **Community Features**: Comments, reposts, and sharing\n- **Free Tier**: Extensive free content\n- **Creator Tools**: Built-in recording and sharing\n\n### Other Platforms\n- **Spotify**: Extensive mainstream catalog, curated playlists\n- **Apple Music**: High-quality audio, exclusive releases\n- **YouTube Music**: Video integration, user-generated content\n\n## Audio Quality Comparison\n\n| Platform | Free Quality | Premium Quality | Offline Support |\n|----------|--------------|---------------|-----------------|\n| SoundCloud | 128kbps | 256kbps | Limited |\n| Spotify | 160kbps | 320kbps | Yes |\n| Apple Music | 256kbps | Lossless | Yes |\n| YouTube Music | 128kbps | 256kbps | Yes |\n\n## User Experience\n\n### SoundCloud\n**Strengths:**\n- Intuitive interface\n- Strong community features\n- Excellent discovery algorithms\n- Free access to most content\n- Mobile and desktop apps\n\n**Weaknesses:**\n- Limited mainstream content\n- Basic playlist features\n- Ad interruptions on free tier\n- Limited offline functionality\n\n### Spotify\n**Strengths:**\n- Comprehensive music library\n- Advanced playlist features\n- Excellent recommendation engine\n- Social sharing capabilities\n- Podcast integration\n\n**Weaknesses:**\n- Limited free tier\n- No video content\n- Less focus on independent artists\n- Premium subscription required for best features\n\n### Apple Music\n**Strengths:**\n- High-quality audio\n- Seamless Apple ecosystem integration\n- Exclusive content\n- Curated playlists\n- Lossless audio support\n\n**Weaknesses:**\n- Apple device dependency\n- Higher subscription cost\n- Limited free tier\n- Less social features\n\n### YouTube Music\n**Strengths:**\n- Video and audio integration\n- Extensive content library\n- User-generated content\n- Google ecosystem integration\n- Free tier available\n\n**Weaknesses:**\n- Video-focused interface\n- Limited offline features\n- Ad interruptions\n- Less music-focused than competitors\n\n## Pricing Comparison\n\n### SoundCloud\n- **Free**: Limited features, ads\n- **SoundCloud Go**: $4.99/month\n- **SoundCloud Go+**: $9.99/month\n\n### Spotify\n- **Free**: Limited features, ads\n- **Premium**: $9.99/month\n- **Family**: $14.99/month (up to 6 accounts)\n\n### Apple Music\n- **Free Trial**: 3 months\n- **Individual**: $10.99/month\n- **Family**: $16.99/month (up to 6 accounts)\n\n### YouTube Music\n- **Free**: Limited features, ads\n- **Premium**: $9.99/month\n- **Family**: $14.99/month (up to 6 accounts)\n\n## Unique Features\n\n### SoundCloud Exclusives\n- **Repost Function**: Share tracks easily\n- **Comments on Waveform**: Time-specific feedback\n- **Creator Tools**: Built-in recording and editing\n- **Community Features**: Follow artists and fans\n- **Free Uploads**: Artists can upload for free\n\n### Platform-Specific Features\n- **Spotify**: Collaborative playlists, Spotify Connect\n- **Apple Music**: Siri integration, spatial audio\n- **YouTube Music**: Video integration, background play\n\n## Content Availability\n\n### SoundCloud\n- **Independent Artists**: Excellent\n- **Mainstream Music**: Limited\n- **Exclusive Content**: High\n- **User-Generated**: Extensive\n- **Podcasts**: Limited\n\n### Other Platforms\n- **Spotify**: Comprehensive mainstream catalog\n- **Apple Music**: High-quality licensed content\n- **YouTube Music**: Extensive video and audio library\n\n## Discovery and Recommendations\n\n### SoundCloud\n- **Algorithm**: Excellent for discovering new artists\n- **Community**: Strong social discovery\n- **Genres**: Wide variety of niche genres\n- **Trending**: Real-time trending tracks\n\n### Comparison\n- **Spotify**: Best overall recommendation engine\n- **Apple Music**: Curated, high-quality recommendations\n- **YouTube Music**: Video-based discovery\n\n## Mobile Experience\n\n### SoundCloud Mobile\n- **Interface**: Clean and intuitive\n- **Offline**: Limited offline functionality\n- **Background Play**: Available on paid plans\n- **Sharing**: Excellent social sharing features\n\n### Other Platforms\n- **Spotify**: Best mobile experience overall\n- **Apple Music**: Seamless iOS integration\n- **YouTube Music**: Video-optimized interface\n\n## Creator Opportunities\n\n### SoundCloud for Creators\n- **Free Uploads**: No cost to upload\n- **Monetization**: Revenue sharing program\n- **Community**: Direct fan interaction\n- **Tools**: Built-in creation tools\n- **Discovery**: Algorithm favors new content\n\n### Other Platforms\n- **Spotify**: Limited creator tools\n- **Apple Music**: Curated selection process\n- **YouTube Music**: Video creation opportunities\n\n## Download and Offline Access\n\n### SoundCloud Limitations\n- **Download Restrictions**: Limited offline access\n- **Quality Options**: Basic quality settings\n- **File Formats**: Limited format support\n- **Storage**: No local file management\n\n### Our Solution\n- **Quality Options**: Multiple bitrates available\n- **Format Support**: MP3, FLAC, WAV, M4A\n- **Offline Access**: Download for offline listening\n- **No Restrictions**: Download any public track\n\n## Future Outlook\n\n### SoundCloud Trends\n- **AI Integration**: Enhanced recommendation algorithms\n- **Creator Tools**: Advanced creation and editing features\n- **Monetization**: Improved revenue sharing\n- **Quality**: Higher audio quality options\n\n### Industry Trends\n- **Lossless Audio**: Growing demand for high-quality audio\n- **Social Features**: Increased social integration\n- **AI Recommendations**: More personalized experiences\n- **Creator Economy**: Better tools for independent artists\n\n## Our Recommendation\n\n### Choose SoundCloud If:\n- You love discovering new and independent artists\n- You want to support emerging talent\n- You enjoy community features and social interaction\n- You're looking for unique and exclusive content\n- You want free access to most content\n\n### Choose Other Platforms If:\n- You prefer mainstream music\n- You need extensive offline functionality\n- You want the highest audio quality\n- You're looking for comprehensive music libraries\n- You prefer curated experiences\n\n## Conclusion\n\nSoundCloud offers a unique value proposition in the music streaming landscape, particularly for those interested in discovering new artists and supporting independent creators. While it may not have the extensive mainstream catalog of Spotify or Apple Music, it excels in community features, artist discovery, and providing a platform for emerging talent.\n\nThe choice between SoundCloud and other platforms ultimately depends on your music preferences, discovery habits, and whether you value community interaction over mainstream content availability. For many music enthusiasts, SoundCloud remains the go-to platform for discovering the next big artist before they hit the mainstream.",
        "excerpt": "Compare SoundCloud with Spotify, Apple Music, and YouTube Music. Discover which platform is best for your music streaming needs.",
        "status": "publish",
        "featured_image": "https://via.placeholder.com/800x400/48bb78/ffffff?text=Platform+Comparison"
      },
      {
        "title": "The Future of Music Downloading: Trends and Predictions",
        "slug": "future-music-downloading-trends-predictions",
        "content": "The music downloading landscape has evolved significantly over the past decade, and the future promises even more exciting developments. In this article, we explore the current trends and make predictions about the future of music downloading.\n\n## Current State of Music Downloading\n\n### The Rise of Streaming\nStreaming has become the dominant way people consume music, but downloading still plays a crucial role:\n\n- **Offline Access**: Downloading enables listening without internet\n- **Quality Control**: Users can choose their preferred audio quality\n- **Ownership**: Downloaded files provide a sense of ownership\n- **Backup**: Local files serve as backups for important music\n\n### Legal Landscape\nThe legal framework around music downloading continues to evolve:\n\n- **Fair Use**: Personal use downloads are generally protected\n- **Copyright Respect**: Users must respect artist rights\n- **Platform Policies**: Each platform has its own terms of service\n- **International Laws**: Different countries have varying regulations\n\n## Emerging Trends\n\n### 1. AI-Powered Quality Enhancement\n**Current State**: Basic quality options (128kbps, 256kbps, 320kbps, FLAC)\n**Future**: AI algorithms that enhance audio quality during download\n\n**Benefits:**\n- Automatic quality optimization\n- Noise reduction and enhancement\n- Dynamic range compression\n- Personalized audio profiles\n\n### 2. Blockchain-Based Music Rights\n**Current State**: Traditional copyright and licensing\n**Future**: Blockchain technology for transparent rights management\n\n**Potential Impact:**\n- Direct artist compensation\n- Transparent royalty distribution\n- Immutable ownership records\n- Smart contracts for licensing\n\n### 3. Cloud-Native Downloading\n**Current State**: Local file storage\n**Future**: Seamless cloud integration\n\n**Features:**\n- Automatic cloud backup\n- Cross-device synchronization\n- Collaborative playlists\n- Smart caching algorithms\n\n### 4. Voice-Controlled Downloads\n**Current State**: Manual search and download\n**Future**: Voice-activated downloading\n\n**Capabilities:**\n- 'Download this song' voice commands\n- Natural language search\n- Contextual recommendations\n- Hands-free operation\n\n## Technology Predictions\n\n### 2024-2025: Enhanced User Experience\n- **Faster Processing**: Sub-second download times\n- **Better Compression**: More efficient file formats\n- **Smart Recommendations**: AI-driven content discovery\n- **Mobile Optimization**: Touch-first interfaces\n\n### 2025-2027: AI Integration\n- **Quality Enhancement**: Real-time audio improvement\n- **Content Analysis**: Automatic genre and mood detection\n- **Personalization**: Custom audio profiles\n- **Predictive Downloads**: Proactive content suggestions\n\n### 2027-2030: Next-Generation Features\n- **Holographic Audio**: 3D audio experiences\n- **Neural Networks**: Advanced audio processing\n- **Quantum Computing**: Ultra-fast processing\n- **Brain-Computer Interfaces**: Direct neural music experiences\n\n## Platform Evolution\n\n### SoundCloud's Future\n**Predicted Developments:**\n- Enhanced creator tools\n- Better monetization options\n- Improved discovery algorithms\n- Higher quality audio options\n- Social commerce integration\n\n### Competing Platforms\n**Spotify**: Focus on podcast integration and social features\n**Apple Music**: Emphasis on spatial audio and lossless quality\n**YouTube Music**: Video-audio integration and creator tools\n\n## User Behavior Changes\n\n### Current Trends\n- **Mobile-First**: 80% of downloads on mobile devices\n- **Quality Focus**: Growing demand for high-quality audio\n- **Social Sharing**: Increased social media integration\n- **Offline Preference**: Downloading for offline listening\n\n### Future Predictions\n- **AI Curation**: Personalized content selection\n- **Immersive Audio**: 3D and spatial audio experiences\n- **Real-Time Collaboration**: Shared listening experiences\n- **Predictive Downloads**: AI-driven content suggestions\n\n## Technical Innovations\n\n### Audio Technology\n**Current**: MP3, FLAC, WAV formats\n**Future**: Next-generation codecs with better compression\n\n**Emerging Formats:**\n- **Opus**: Superior compression efficiency\n- **AAC Enhanced**: Better quality at lower bitrates\n- **Neural Audio**: AI-generated audio enhancement\n- **Spatial Audio**: 3D audio positioning\n\n### Download Technology\n**Current**: HTTP-based downloads\n**Future**: Advanced protocols and methods\n\n**Innovations:**\n- **P2P Integration**: Peer-to-peer downloading\n- **Edge Computing**: Faster local processing\n- **Quantum Networks**: Ultra-fast transfers\n- **Blockchain Storage**: Decentralized file systems\n\n## Privacy and Security\n\n### Current Concerns\n- Data collection by platforms\n- Privacy of download history\n- Security of downloaded files\n- Tracking of user behavior\n\n### Future Solutions\n- **Zero-Knowledge Downloads**: No platform tracking\n- **Encrypted Storage**: Secure local file protection\n- **Decentralized Networks**: No central authority\n- **Privacy-First Design**: Built-in privacy protection\n\n## Economic Impact\n\n### Creator Economy\n**Current**: Limited monetization for independent artists\n**Future**: Enhanced revenue opportunities\n\n**Developments:**\n- Direct fan payments\n- NFT integration\n- Smart contract royalties\n- Micro-transactions\n\n### Platform Economics\n**Current**: Subscription-based models\n**Future**: Diverse revenue streams\n\n**Trends:**\n- Freemium models\n- Creator revenue sharing\n- Advertising integration\n- Premium features\n\n## Regulatory Changes\n\n### Current Regulations\n- Copyright laws vary by country\n- Platform terms of service\n- Fair use provisions\n- DMCA compliance\n\n### Future Predictions\n- **Global Standards**: Unified international laws\n- **AI Regulation**: Guidelines for AI-generated content\n- **Privacy Laws**: Enhanced data protection\n- **Creator Rights**: Better protection for artists\n\n## Environmental Considerations\n\n### Current Impact\n- Server energy consumption\n- Data center carbon footprint\n- Electronic waste from devices\n- Network infrastructure energy use\n\n### Future Solutions\n- **Green Computing**: Energy-efficient processing\n- **Renewable Energy**: Solar and wind-powered servers\n- **Efficient Compression**: Reduced data transfer\n- **Sustainable Hardware**: Eco-friendly devices\n\n## Our Vision for the Future\n\n### Short-Term Goals (2024-2025)\n- Implement AI-powered quality enhancement\n- Add voice-controlled downloading\n- Improve mobile user experience\n- Enhance privacy protection\n\n### Medium-Term Goals (2025-2027)\n- Integrate blockchain technology\n- Develop spatial audio support\n- Create collaborative features\n- Build predictive algorithms\n\n### Long-Term Goals (2027-2030)\n- Pioneer holographic audio\n- Implement neural interfaces\n- Develop quantum processing\n- Create immersive experiences\n\n## Conclusion\n\nThe future of music downloading is bright and full of possibilities. As technology continues to evolve, we can expect:\n\n- **Better Quality**: Enhanced audio experiences\n- **Smarter Systems**: AI-powered personalization\n- **More Privacy**: Enhanced data protection\n- **Greater Accessibility**: Easier and more intuitive interfaces\n- **Stronger Communities**: Better creator-fan connections\n\nThe key to success in this evolving landscape will be adapting to new technologies while maintaining the core values of quality, privacy, and user experience. As we look toward the future, we're excited to be part of this journey and committed to providing the best possible music downloading experience.\n\nStay tuned for more updates as we continue to innovate and improve our platform!",
        "excerpt": "Explore the future of music downloading with AI, blockchain, and emerging technologies. Predictions for 2024-2030 and industry trends.",
        "status": "publish",
        "featured_image": "https://via.placeholder.com/800x400/9f7aea/ffffff?text=Future+of+Music"
      }
    ],
    "menus": [
      {
        "name": "Primary Menu",
        "location": "primary",
        "items": [
          {
            "title": "Home",
            "url": "/",
            "type": "custom"
          },
          {
            "title": "Downloader",
            "url": "/downloader/",
            "type": "custom"
          },
          {
            "title": "Blog",
            "url": "/blog/",
            "type": "custom"
          },
          {
            "title": "About Us",
            "url": "/about/",
            "type": "custom"
          },
          {
            "title": "FAQ",
            "url": "/faq/",
            "type": "custom"
          },
          {
            "title": "Contact",
            "url": "/contact/",
            "type": "custom"
          }
        ]
      },
      {
        "name": "Footer Menu",
        "location": "footer",
        "items": [
          {
            "title": "Privacy Policy",
            "url": "/privacy-policy/",
            "type": "custom"
          },
          {
            "title": "Terms of Service",
            "url": "/terms-of-service/",
            "type": "custom"
          },
          {
            "title": "DMCA",
            "url": "/dmca/",
            "type": "custom"
          }
        ]
      }
    ],
    "theme_options": {
      "hero_title": "Download Music from SoundCloud",
      "hero_description": "Download your favorite tracks from SoundCloud in high quality. Fast, secure, and easy to use.",
      "site_logo": "",
      "contact_email": "support@soundcloud-downloader.com",
      "social_links": {
        "facebook": "",
        "twitter": "",
        "instagram": "",
        "youtube": ""
      },
      "footer_text": "© 2024 SoundCloud Downloader. All rights reserved.",
      "analytics_code": "",
      "custom_css": ""
    },
    "widgets": [
      {
        "sidebar": "sidebar-1",
        "widgets": [
          {
            "type": "text",
            "title": "About Our Service",
            "content": "We provide the best SoundCloud downloading experience with high-quality audio formats and fast processing."
          },
          {
            "type": "recent-posts",
            "title": "Latest Posts",
            "number": 5
          }
        ]
      },
      {
        "sidebar": "footer-widgets",
        "widgets": [
          {
            "type": "text",
            "title": "Quick Links",
            "content": "<ul><li><a href='/downloader/'>Downloader</a></li><li><a href='/about/'>About Us</a></li><li><a href='/contact/'>Contact</a></li></ul>"
          },
          {
            "type": "text",
            "title": "Legal",
            "content": "<ul><li><a href='/privacy-policy/'>Privacy Policy</a></li><li><a href='/terms-of-service/'>Terms of Service</a></li></ul>"
          }
        ]
      }
    ],
    "customizer_settings": {
      "colors": {
        "primary_color": "#667eea",
        "secondary_color": "#764ba2",
        "accent_color": "#ff6b6b",
        "text_color": "#333333",
        "background_color": "#f8fafc"
      },
      "typography": {
        "body_font": "Inter",
        "heading_font": "Inter",
        "body_size": "16px",
        "heading_size": "24px"
      },
      "layout": {
        "container_width": "1200px",
        "sidebar_position": "right",
        "header_style": "gradient"
      }
    }
  }
}
